Metadata-Version: 1.1
Name: junitparsershubhindia
Version: 2.1.3
Summary: Manipulates JUnit/xUnit Result XML files
Home-page: https://github.com/shubhindia/junitparser
Author: Shubham Gopale
Author-email: shubhindia123@gmail.com
License: Apache 2.0
Keywords: junit xunit xml parser
Platform: UNKNOWN
Classifier: Development Status :: 5 - Production/Stable
Classifier: Intended Audience :: Developers
Classifier: License :: OSI Approved :: Apache Software License
Classifier: Topic :: Text Processing
Classifier: Programming Language :: Python :: 2
Classifier: Programming Language :: Python :: 3
